[{"id":10000,"name":"Catarina Helm","itemType":"armor","dur":100,"weight":4.5,"sell":100,"armorType":"head","armorSet":"Catarina","iconId":1000,"defN":22,"defSl":25.3,"defSt":21.8,"defTh":22,"defM":12,"defF":13,"defL":7,"defP":8,"defT":9,"defB":13,"defC":0,"upgradeId":100,"stRec":-1},{"id":11000,"name":"Catarina Armor","itemType":"armor","dur":100,"weight":11.7,"sell":100,"armorType":"chest","armorSet":"Catarina","iconId":1001,"defN":57,"defSl":65.5,"defSt":56.4,"defTh":57,"defM":31,"defF":37,"defL":19,"defP":21,"defT":24,"defB":34,"defC":0,"upgradeId":100,"stRec":-1},{"id":12000,"name":"Catarina Gauntlets","itemType":"armor","dur":100,"weight":6.9,"sell":100,"armorType":"hands","armorSet":"Catarina","iconId":1002,"defN":34,"defSl":39.1,"defSt":33.7,"defTh":34,"defM":18,"defF":21,"defL":12,"defP":13,"defT":13,"defB":21,"defC":0,"upgradeId":100,"stRec":-1},{"id":13000,"name":"Catarina Leggings","itemType":"armor","dur":100,"weight":6.9,"sell":100,"armorType":"legs","armorSet":"Catarina","iconId":1003,"defN":34,"defSl":39.1,"defSt":33.7,"defTh":34,"defM":18,"defF":21,"defL":12,"defP":13,"defT":13,"defB":21,"defC":0,"upgradeId":100,"stRec":-1},{"id":20000,"name":"Paladin Helm","itemType":"armor","dur":100,"weight":5,"sell":100,"armorType":"head","armorSet":"Paladin","iconId":1004,"defN":22,"defSl":25.3,"defSt":20.9,"defTh":22,"defM":12,"defF":13,"defL":7,"defP":8,"defT":9,"defB":13,"defC":22,"upgradeId":100,"stRec":-1},{"id":21000,"name":"Paladin Armor","itemType":"armor","dur":100,"weight":12.9,"sell":100,"armorType":"chest","armorSet":"Paladin","iconId":1005,"defN":59,"defSl":67.9,"defSt":56.1,"defTh":59,"defM":31,"defF":37,"defL":19,"defP":20,"defT":24,"defB":34,"defC":57,"upgradeId":100,"stRec":-1},{"id":22000,"name":"Paladin Gauntlets","itemType":"armor","dur":100,"weight":7.6,"sell":100,"armorType":"hands","armorSet":"Paladin","iconId":1006,"defN":35,"defSl":40.2,"defSt":33.2,"defTh":35,"defM":19,"defF":21,"defL":12,"defP":12,"defT":13,"defB":21,"defC":34,"upgradeId":100,"stRec":-1},{"id":23000,"name":"Paladin Leggings","itemType":"armor","dur":100,"weight":7.6,"sell":100,"armorType":"legs","armorSet":"Paladin","iconId":1007,"defN":35,"defSl":40.2,"defSt":33.2,"defTh":35,"defM":19,"defF":21,"defL":12,"defP":12,"defT":13,"defB":21,"defC":34,"upgradeId":100,"stRec":-1},{"id":40000,"name":"Dark Mask","itemType":"armor","dur":100,"weight":3.8,"sell":100,"armorType":"head","armorSet":"Dark","iconId":1012,"defN":18,"defSl":19.8,"defSt":18,"defTh":16.9,"defM":12,"defF":12,"defL":10,"defP":6,"defT":8,"defB":12,"defC":0,"upgradeId":100},{"id":41000,"name":"Dark Armor","itemType":"armor","dur":100,"weight":9.8,"sell":100,"armorType":"chest","armorSet":"Dark","iconId":1013,"defN":45,"defSl":49.5,"defSt":45,"defTh":42.3,"defM":30,"defF":31,"defL":27,"defP":16,"defT":21,"defB":30,"defC":0,"upgradeId":100},{"id":42000,"name":"Dark Gauntlets","itemType":"armor","dur":100,"weight":5.8,"sell":100,"armorType":"hands","armorSet":"Dark","iconId":1014,"defN":27,"defSl":29.7,"defSt":27,"defTh":25.4,"defM":18,"defF":18,"defL":15,"defP":9,"defT":12,"defB":18,"defC":0,"upgradeId":100},{"id":43000,"name":"Dark Leggings","itemType":"armor","dur":100,"weight":5.8,"sell":100,"armorType":"legs","armorSet":"Dark","iconId":1015,"defN":27,"defSl":29.7,"defSt":27,"defTh":25.4,"defM":18,"defF":18,"defL":15,"defP":9,"defT":12,"defB":18,"defC":0,"upgradeId":100},{"id":50000,"name":"Brigand Hood","itemType":"armor","dur":100,"weight":1.2,"sell":100,"armorType":"head","armorSet":"Brigand","iconId":1153,"defN":9,"defSl":9,"defSt":9.9,"defTh":8.1,"defM":8,"defF":5,"defL":6,"defP":0,"defT":8,"defB":8,"defC":0,"upgradeId":0},{"id":51000,"name":"Brigand Armor","itemType":"armor","dur":100,"weight":3.1,"sell":100,"armorType":"chest","armorSet":"Brigand","iconId":1154,"defN":23,"defSl":23,"defSt":25.3,"defTh":20.7,"defM":20,"defF":13,"defL":17,"defP":0,"defT":20,"defB":20,"defC":0,"upgradeId":0},{"id":52000,"name":"Brigand Gauntlets","itemType":"armor","dur":100,"weight":1.8,"sell":100,"armorType":"hands","armorSet":"Brigand","iconId":1155,"defN":14,"defSl":14,"defSt":15.4,"defTh":12.6,"defM":12,"defF":8,"defL":10,"defP":0,"defT":12,"defB":12,"defC":0,"upgradeId":0},{"id":53000,"name":"Brigand Trousers","itemType":"armor","dur":100,"weight":1.8,"sell":100,"armorType":"legs","armorSet":"Brigand","iconId":1156,"defN":14,"defSl":14,"defSt":15.4,"defTh":12.6,"defM":12,"defF":8,"defL":10,"defP":0,"defT":12,"defB":12,"defC":0,"upgradeId":0},{"id":60000,"name":"Shadow Mask","itemType":"armor","dur":100,"weight":0.9,"sell":100,"armorType":"head","armorSet":"Shadow","iconId":1157,"defN":9,"defSl":9,"defSt":9.9,"defTh":9,"defM":5,"defF":6,"defL":6,"defP":0,"defT":18,"defB":15,"defC":0,"upgradeId":100},{"id":61000,"name":"Shadow Garb","itemType":"armor","dur":100,"weight":2.3,"sell":100,"armorType":"chest","armorSet":"Shadow","iconId":1158,"defN":23,"defSl":23,"defSt":25.3,"defTh":23,"defM":12,"defF":16,"defL":17,"defP":0,"defT":47,"defB":39,"defC":0,"upgradeId":100},{"id":62000,"name":"Shadow Gauntlets","itemType":"armor","dur":100,"weight":1.4,"sell":100,"armorType":"hands","armorSet":"Shadow","iconId":1159,"defN":13,"defSl":13,"defSt":14.3,"defTh":13,"defM":7,"defF":9,"defL":10,"defP":0,"defT":28,"defB":23,"defC":0,"upgradeId":100},{"id":63000,"name":"Shadow Leggings","itemType":"armor","dur":100,"weight":1.4,"sell":100,"armorType":"legs","armorSet":"Shadow","iconId":1160,"defN":13,"defSl":13,"defSt":14.3,"defTh":13,"defM":7,"defF":9,"defL":10,"defP":0,"defT":28,"defB":23,"defC":0,"upgradeId":100},{"id":70000,"name":"Black Iron Helm","itemType":"armor","dur":100,"weight":6,"sell":100,"armorType":"head","armorSet":"Black Iron","iconId":1024,"defN":27,"defSl":31.1,"defSt":25.7,"defTh":27,"defM":11,"defF":19,"defL":8,"defP":12,"defT":10,"defB":17,"defC":5,"upgradeId":100,"stRec":-1},{"id":71000,"name":"Black Iron Armor","itemType":"armor","dur":100,"weight":15.6,"sell":100,"armorType":"chest","armorSet":"Black Iron","iconId":1025,"defN":68,"defSl":78.2,"defSt":64.6,"defTh":68,"defM":30,"defF":51,"defL":21,"defP":31,"defT":25,"defB":43,"defC":13,"upgradeId":100,"stRec":-2},{"id":72000,"name":"Black Iron Gauntlets","itemType":"armor","dur":100,"weight":9.2,"sell":100,"armorType":"hands","armorSet":"Black Iron","iconId":1026,"defN":40,"defSl":46,"defSt":38,"defTh":40,"defM":17,"defF":30,"defL":13,"defP":18,"defT":14,"defB":25,"defC":8,"upgradeId":100,"stRec":-1},{"id":73000,"name":"Black Iron Leggings","itemType":"armor","dur":100,"weight":9.2,"sell":100,"armorType":"legs","armorSet":"Black Iron","iconId":1027,"defN":40,"defSl":46,"defSt":38,"defTh":40,"defM":17,"defF":30,"defL":13,"defP":18,"defT":14,"defB":25,"defC":8,"upgradeId":100,"stRec":-1},{"id":80000,"name":"Smough's Helm","itemType":"armor","dur":100,"weight":6.8,"sell":1,"armorType":"head","armorSet":"Smough's","iconId":1028,"defN":40,"defSl":46,"defSt":34.8,"defTh":40,"defM":19,"defF":26,"defL":21,"defP":14,"defT":12,"defB":21,"defC":5,"upgradeId":-1,"stRec":-1},{"id":81000,"name":"Smough's Armor","itemType":"armor","dur":100,"weight":17.6,"sell":1,"armorType":"chest","armorSet":"Smough's","iconId":1029,"defN":106,"defSl":121.9,"defSt":92.2,"defTh":106,"defM":52,"defF":66,"defL":59,"defP":35,"defT":28,"defB":54,"defC":9,"upgradeId":-1,"stRec":-2},{"id":82000,"name":"Smough's Gauntlets","itemType":"armor","dur":100,"weight":10.4,"sell":1,"armorType":"hands","armorSet":"Smough's","iconId":1030,"defN":61,"defSl":70.2,"defSt":53.1,"defTh":61,"defM":31,"defF":40,"defL":33,"defP":21,"defT":16,"defB":33,"defC":5,"upgradeId":-1,"stRec":-1},{"id":83000,"name":"Smough's Leggings","itemType":"armor","dur":100,"weight":10.4,"sell":1,"armorType":"legs","armorSet":"Smough's","iconId":1031,"defN":61,"defSl":70.2,"defSt":53.1,"defTh":61,"defM":31,"defF":40,"defL":33,"defP":21,"defT":16,"defB":33,"defC":5,"upgradeId":-1,"stRec":-1},{"id":90000,"name":"Six-Eyed Helm of the Channelers","itemType":"armor","dur":100,"weight":3.9,"sell":1,"armorType":"head","armorSet":"Channeler's","iconId":1032,"defN":20,"defSl":22.8,"defSt":19.2,"defTh":20,"defM":18,"defF":17,"defL":13,"defP":5,"defT":13,"defB":15,"defC":0,"upgradeId":-1},{"id":91000,"name":"Robe of the Channelers","itemType":"armor","dur":100,"weight":10.1,"sell":1,"armorType":"chest","armorSet":"Channeler's","iconId":1033,"defN":53,"defSl":60.4,"defSt":50.9,"defTh":53,"defM":45,"defF":45,"defL":35,"defP":12,"defT":33,"defB":38,"defC":0,"upgradeId":-1},{"id":92000,"name":"Gauntlets of the Channelers","itemType":"armor","dur":100,"weight":3,"sell":1,"armorType":"hands","armorSet":"Channeler's","iconId":1034,"defN":17,"defSl":19.4,"defSt":16.3,"defTh":17,"defM":13,"defF":13,"defL":0,"defP":3,"defT":10,"defB":12,"defC":0,"upgradeId":-1},{"id":93000,"name":"Waistcloth of the Channelers","itemType":"armor","dur":100,"weight":6,"sell":1,"armorType":"legs","armorSet":"Channeler's","iconId":1035,"defN":32,"defSl":36.5,"defSt":30.7,"defTh":32,"defM":27,"defF":27,"defL":30,"defP":7,"defT":20,"defB":23,"defC":0,"upgradeId":-1},{"id":100000,"name":"Helm of Favor","itemType":"armor","dur":100,"weight":4.5,"sell":1000,"armorType":"head","armorSet":"Favor","iconId":1036,"defN":18,"defSl":20.9,"defSt":17.1,"defTh":18,"defM":10,"defF":11,"defL":7,"defP":8,"defT":8,"defB":11,"defC":8,"upgradeId":100},{"id":101000,"name":"Embraced Armor of Favor","itemType":"armor","dur":100,"weight":11.7,"sell":1000,"armorType":"chest","armorSet":"Favor","iconId":1037,"defN":48,"defSl":55.7,"defSt":45.6,"defTh":48,"defM":23,"defF":30,"defL":19,"defP":20,"defT":22,"defB":28,"defC":22,"upgradeId":100},{"id":102000,"name":"Gauntlets of Favor","itemType":"armor","dur":100,"weight":5,"sell":1000,"armorType":"hands","armorSet":"Favor","iconId":1038,"defN":21,"defSl":24.4,"defSt":19.9,"defTh":21,"defM":10,"defF":12,"defL":8,"defP":8,"defT":10,"defB":11,"defC":10,"upgradeId":100},{"id":103000,"name":"Leggings of Favor","itemType":"armor","dur":100,"weight":6.9,"sell":1000,"armorType":"legs","armorSet":"Favor","iconId":1039,"defN":28,"defSl":32.5,"defSt":26.6,"defTh":28,"defM":14,"defF":18,"defL":11,"defP":11,"defT":14,"defB":15,"defC":14,"upgradeId":100},{"id":110000,"name":"Helm of the Wise","itemType":"armor","dur":100,"weight":5.1,"sell":100,"armorType":"head","armorSet":"Adventurer's","iconId":1040,"defN":18,"defSl":20.7,"defSt":17.1,"defTh":18,"defM":12,"defF":13,"defL":10,"defP":8,"defT":7,"defB":11,"defC":18,"upgradeId":-1},{"id":111000,"name":"Armor of the Glorious","itemType":"armor","dur":100,"weight":13.3,"sell":100,"armorType":"chest","armorSet":"Adventurer's","iconId":1041,"defN":47,"defSl":54.1,"defSt":44.6,"defTh":47,"defM":31,"defF":34,"defL":25,"defP":20,"defT":19,"defB":28,"defC":24,"upgradeId":-1,"stRec":-1},{"id":112000,"name":"Gauntlets of the Vanquisher","itemType":"armor","dur":100,"weight":3,"sell":100,"armorType":"hands","armorSet":"Adventurer's","iconId":1042,"defN":11,"defSl":12.7,"defSt":10.5,"defTh":11,"defM":7,"defF":7,"defL":6,"defP":4,"defT":5,"defB":6,"defC":4,"upgradeId":-1},{"id":113000,"name":"Boots of the Explorer","itemType":"armor","dur":100,"weight":4,"sell":100,"armorType":"legs","armorSet":"Adventurer's","iconId":1043,"defN":14,"defSl":16.1,"defSt":13.3,"defTh":14,"defM":10,"defF":11,"defL":7,"defP":6,"defT":6,"defB":8,"defC":5,"upgradeId":-1},{"id":120000,"name":"Stone Helm","itemType":"armor","dur":100,"weight":6.8,"sell":100,"armorType":"head","armorSet":"Stone","iconId":1044,"defN":35,"defSl":40.3,"defSt":32.9,"defTh":35,"defM":17,"defF":21,"defL":21,"defP":15,"defT":6,"defB":17,"defC":0,"upgradeId":-1,"stRec":-1},{"id":121000,"name":"Stone Armor","itemType":"armor","dur":100,"weight":17.6,"sell":100,"armorType":"chest","armorSet":"Stone","iconId":1045,"defN":91,"defSl":104.7,"defSt":85.5,"defTh":91,"defM":45,"defF":54,"defL":54,"defP":39,"defT":16,"defB":45,"defC":0,"upgradeId":-1,"stRec":-2},{"id":122000,"name":"Stone Gauntlets","itemType":"armor","dur":100,"weight":10.4,"sell":100,"armorType":"hands","armorSet":"Stone","iconId":1046,"defN":54,"defSl":62.1,"defSt":50.8,"defTh":54,"defM":27,"defF":33,"defL":33,"defP":23,"defT":10,"defB":27,"defC":0,"upgradeId":-1,"stRec":-1},{"id":123000,"name":"Stone Leggings","itemType":"armor","dur":100,"weight":10.4,"sell":100,"armorType":"legs","armorSet":"Stone","iconId":1047,"defN":54,"defSl":62.1,"defSt":50.8,"defTh":54,"defM":27,"defF":33,"defL":33,"defP":23,"defT":10,"defB":27,"defC":0,"upgradeId":-1,"stRec":-1},{"id":130000,"name":"Crystalline Helm","itemType":"armor","dur":100,"weight":4.2,"sell":1,"armorType":"head","armorSet":"Crystalline","iconId":1048,"defN":25,"defSl":28.8,"defSt":21.3,"defTh":25,"defM":8,"defF":6,"defL":2,"defP":6,"defT":0,"defB":6,"defC":0,"upgradeId":-1},{"id":131000,"name":"Crystalline Armor","itemType":"armor","dur":100,"weight":10.9,"sell":1,"armorType":"chest","armorSet":"Crystalline","iconId":1049,"defN":59,"defSl":67.9,"defSt":50.1,"defTh":59,"defM":21,"defF":15,"defL":7,"defP":16,"defT":0,"defB":15,"defC":0,"upgradeId":-1},{"id":132000,"name":"Crystalline Gauntlets","itemType":"armor","dur":100,"weight":6.4,"sell":1,"armorType":"hands","armorSet":"Crystalline","iconId":1050,"defN":37,"defSl":42.6,"defSt":31.5,"defTh":37,"defM":12,"defF":9,"defL":4,"defP":9,"defT":0,"defB":9,"defC":0,"upgradeId":-1},{"id":133000,"name":"Crystalline Leggings","itemType":"armor","dur":100,"weight":6.4,"sell":1,"armorType":"legs","armorSet":"Crystalline","iconId":1051,"defN":37,"defSl":42.6,"defSt":31.5,"defTh":37,"defM":12,"defF":9,"defL":4,"defP":9,"defT":0,"defB":9,"defC":0,"upgradeId":-1},{"id":140000,"name":"Mask of the Sealer","itemType":"armor","dur":100,"weight":1.5,"sell":100,"armorType":"head","armorSet":"Crimson","iconId":1052,"defN":12,"defSl":12,"defSt":13.2,"defTh":12,"defM":12,"defF":7,"defL":9,"defP":0,"defT":8,"defB":8,"defC":8,"upgradeId":100},{"id":141000,"name":"Crimson Robe","itemType":"armor","dur":100,"weight":3.9,"sell":100,"armorType":"chest","armorSet":"Crimson","iconId":1053,"defN":32,"defSl":32,"defSt":35.2,"defTh":32,"defM":33,"defF":19,"defL":24,"defP":0,"defT":21,"defB":21,"defC":21,"upgradeId":100},{"id":142000,"name":"Crimson Gloves","itemType":"armor","dur":100,"weight":0.8,"sell":100,"armorType":"hands","armorSet":"Crimson","iconId":1054,"defN":7,"defSl":7,"defSt":7.7,"defTh":7,"defM":7,"defF":4,"defL":5,"defP":0,"defT":4,"defB":4,"defC":4,"upgradeId":100},{"id":143000,"name":"Crimson Waistcloth","itemType":"armor","dur":100,"weight":3.5,"sell":100,"armorType":"legs","armorSet":"Crimson","iconId":1055,"defN":29,"defSl":29,"defSt":31.9,"defTh":29,"defM":29,"defF":17,"defL":21,"defP":0,"defT":19,"defB":19,"defC":19,"upgradeId":100},{"id":150000,"name":"Mask of Velka","itemType":"armor","dur":100,"weight":2.5,"sell":100,"armorType":"head","armorSet":"Black","iconId":1056,"defN":12,"defSl":12,"defSt":13.1,"defTh":12,"defM":12,"defF":10,"defL":7,"defP":0,"defT":9,"defB":9,"defC":20,"upgradeId":100},{"id":151000,"name":"Black Cleric Robe","itemType":"armor","dur":100,"weight":3.9,"sell":100,"armorType":"chest","armorSet":"Black","iconId":1057,"defN":23,"defSl":23,"defSt":25.1,"defTh":23,"defM":29,"defF":25,"defL":19,"defP":0,"defT":22,"defB":22,"defC":13,"upgradeId":100},{"id":152000,"name":"Black Manchette","itemType":"armor","dur":100,"weight":1.8,"sell":100,"armorType":"hands","armorSet":"Black","iconId":1058,"defN":11,"defSl":11,"defSt":12,"defTh":11,"defM":14,"defF":11,"defL":9,"defP":0,"defT":10,"defB":10,"defC":5,"upgradeId":100},{"id":153000,"name":"Black Tights","itemType":"armor","dur":100,"weight":2.8,"sell":100,"armorType":"legs","armorSet":"Black","iconId":1059,"defN":16,"defSl":16,"defSt":17.4,"defTh":16,"defM":22,"defF":17,"defL":13,"defP":0,"defT":15,"defB":15,"defC":9,"upgradeId":100},{"id":160000,"name":"Iron Helm","itemType":"armor","dur":100,"weight":4.5,"sell":100,"armorType":"head","armorSet":"Iron","iconId":1060,"defN":14,"defSl":14,"defSt":14,"defTh":13.7,"defM":10,"defF":10,"defL":9,"defP":8,"defT":8,"defB":12,"defC":2,"upgradeId":0},{"id":161000,"name":"Armor of the Sun","itemType":"armor","dur":100,"weight":9,"sell":100,"armorType":"chest","armorSet":"Iron","iconId":1061,"defN":35,"defSl":35,"defSt":35,"defTh":34.3,"defM":21,"defF":21,"defL":19,"defP":16,"defT":16,"defB":23,"defC":10,"upgradeId":0},{"id":162000,"name":"Iron Bracelet","itemType":"armor","dur":100,"weight":4.3,"sell":100,"armorType":"hands","armorSet":"Iron","iconId":1062,"defN":17,"defSl":17,"defSt":17,"defTh":16.7,"defM":10,"defF":10,"defL":9,"defP":7,"defT":7,"defB":11,"defC":2,"upgradeId":0},{"id":163000,"name":"Iron Leggings","itemType":"armor","dur":100,"weight":5.3,"sell":100,"armorType":"legs","armorSet":"Iron","iconId":1063,"defN":21,"defSl":21,"defSt":21,"defTh":20.6,"defM":12,"defF":12,"defL":11,"defP":9,"defT":9,"defB":14,"defC":2,"upgradeId":0},{"id":170000,"name":"Chain Helm","itemType":"armor","dur":100,"weight":3,"sell":100,"armorType":"head","armorSet":"Chain","iconId":1073,"defN":12,"defSl":14.4,"defSt":12,"defTh":11.6,"defM":10,"defF":8,"defL":3,"defP":5,"defT":6,"defB":10,"defC":0,"upgradeId":0},{"id":171000,"name":"Chain Armor","itemType":"armor","dur":100,"weight":6,"sell":100,"armorType":"chest","armorSet":"Chain","iconId":1074,"defN":30,"defSl":36,"defSt":30,"defTh":29.1,"defM":21,"defF":16,"defL":7,"defP":9,"defT":12,"defB":20,"defC":0,"upgradeId":0},{"id":172000,"name":"Leather Gauntlets","itemType":"armor","dur":100,"weight":3.6,"sell":100,"armorType":"hands","armorSet":"Chain","iconId":1075,"defN":12,"defSl":14.4,"defSt":12,"defTh":11.6,"defM":10,"defF":8,"defL":4,"defP":5,"defT":7,"defB":12,"defC":0,"upgradeId":0},{"id":173000,"name":"Chain Leggings","itemType":"armor","dur":100,"weight":4.6,"sell":100,"armorType":"legs","armorSet":"Chain","iconId":1076,"defN":18,"defSl":21.6,"defSt":18,"defTh":17.5,"defM":14,"defF":12,"defL":5,"defP":7,"defT":9,"defB":15,"defC":0,"upgradeId":0},{"id":180000,"name":"Cleric Helm","itemType":"armor","dur":100,"weight":4.8,"sell":100,"armorType":"head","armorSet":"Cleric","iconId":1113,"defN":15,"defSl":17.2,"defSt":15,"defTh":15,"defM":9,"defF":8,"defL":6,"defP":8,"defT":6,"defB":9,"defC":0,"upgradeId":0,"stRec":-1},{"id":181000,"name":"Cleric Armor","itemType":"armor","dur":100,"weight":12.5,"sell":100,"armorType":"chest","armorSet":"Cleric","iconId":1114,"defN":40,"defSl":46,"defSt":40,"defTh":40,"defM":23,"defF":21,"defL":15,"defP":20,"defT":16,"defB":23,"defC":0,"upgradeId":0,"stRec":-1},{"id":182000,"name":"Cleric Gauntlets","itemType":"armor","dur":100,"weight":7.4,"sell":100,"armorType":"hands","armorSet":"Cleric","iconId":1115,"defN":24,"defSl":27.6,"defSt":24,"defTh":24,"defM":13,"defF":12,"defL":9,"defP":12,"defT":9,"defB":14,"defC":0,"upgradeId":0,"stRec":-1},{"id":183000,"name":"Cleric Leggings","itemType":"armor","dur":100,"weight":7.4,"sell":100,"armorType":"legs","armorSet":"Cleric","iconId":1116,"defN":24,"defSl":27.6,"defSt":24,"defTh":24,"defM":13,"defF":12,"defL":9,"defP":12,"defT":9,"defB":14,"defC":0,"upgradeId":0,"stRec":-1},{"id":190000,"name":"Sunlight Maggot","itemType":"armor","dur":100,"weight":1.4,"sell":1000,"armorType":"head","armorSet":"","iconId":1072,"defN":6,"defSl":6,"defSt":6,"defTh":6,"defM":5,"defF":24,"defL":13,"defP":0,"defT":0,"defB":0,"defC":0,"upgradeId":-1},{"id":200000,"name":"Helm of Thorns","itemType":"armor","dur":100,"weight":4.1,"sell":100,"armorType":"head","armorSet":"Thorns","iconId":1089,"defN":17,"defSl":18.5,"defSt":16.1,"defTh":17,"defM":10,"defF":12,"defL":8,"defP":6,"defT":7,"defB":10,"defC":0,"upgradeId":100},{"id":201000,"name":"Armor of Thorns","itemType":"armor","dur":100,"weight":10.5,"sell":100,"armorType":"chest","armorSet":"Thorns","iconId":1090,"defN":45,"defSl":49.1,"defSt":42.7,"defTh":45,"defM":28,"defF":33,"defL":20,"defP":16,"defT":18,"defB":26,"defC":0,"upgradeId":100},{"id":202000,"name":"Gauntlets of Thorns","itemType":"armor","dur":100,"weight":6.2,"sell":100,"armorType":"hands","armorSet":"Thorns","iconId":1091,"defN":26,"defSl":28.3,"defSt":24.7,"defTh":26,"defM":16,"defF":18,"defL":12,"defP":9,"defT":10,"defB":16,"defC":0,"upgradeId":100},{"id":203000,"name":"Leggings of Thorns","itemType":"armor","dur":100,"weight":6.2,"sell":100,"armorType":"legs","armorSet":"Thorns","iconId":1092,"defN":26,"defSl":28.3,"defSt":24.7,"defTh":26,"defM":16,"defF":18,"defL":12,"defP":9,"defT":10,"defB":16,"defC":0,"upgradeId":100},{"id":210000,"name":"Standard Helm","itemType":"armor","dur":100,"weight":3.5,"sell":100,"armorType":"head","armorSet":"Hard Leather","iconId":1161,"defN":14,"defSl":16,"defSt":8,"defTh":14,"defM":8,"defF":8,"defL":3,"defP":5,"defT":8,"defB":9,"defC":0,"upgradeId":0},{"id":211000,"name":"Hard Leather Armor","itemType":"armor","dur":100,"weight":5.9,"sell":100,"armorType":"chest","armorSet":"Hard Leather","iconId":1162,"defN":26,"defSl":26,"defSt":27.6,"defTh":26,"defM":20,"defF":13,"defL":23,"defP":0,"defT":20,"defB":23,"defC":0,"upgradeId":0},{"id":212000,"name":"Hard Leather Gauntlets","itemType":"armor","dur":100,"weight":3.5,"sell":100,"armorType":"hands","armorSet":"Hard Leather","iconId":1163,"defN":13,"defSl":13,"defSt":13.8,"defTh":13,"defM":12,"defF":7,"defL":13,"defP":0,"defT":12,"defB":14,"defC":0,"upgradeId":0},{"id":213000,"name":"Hard Leather Boots","itemType":"armor","dur":100,"weight":3.5,"sell":100,"armorType":"legs","armorSet":"Hard Leather","iconId":1164,"defN":13,"defSl":13,"defSt":13.8,"defTh":13,"defM":12,"defF":7,"defL":13,"defP":0,"defT":12,"defB":14,"defC":0,"upgradeId":0},{"id":220000,"name":"Sorcerer Hat","itemType":"armor","dur":100,"weight":0.9,"sell":100,"armorType":"head","armorSet":"Sorcerer","iconId":1117,"defN":8,"defSl":8.3,"defSt":8.6,"defTh":8,"defM":10,"defF":5,"defL":6,"defP":0,"defT":5,"defB":6,"defC":0,"upgradeId":0},{"id":221000,"name":"Sorcerer Cloak","itemType":"armor","dur":100,"weight":2.3,"sell":100,"armorType":"chest","armorSet":"Sorcerer","iconId":1118,"defN":20,"defSl":20.8,"defSt":21.6,"defTh":20,"defM":27,"defF":13,"defL":17,"defP":0,"defT":12,"defB":16,"defC":0,"upgradeId":0},{"id":222000,"name":"Sorcerer Gauntlets","itemType":"armor","dur":100,"weight":1.4,"sell":100,"armorType":"hands","armorSet":"Sorcerer","iconId":1119,"defN":12,"defSl":12.5,"defSt":13,"defTh":12,"defM":16,"defF":8,"defL":10,"defP":0,"defT":7,"defB":9,"defC":0,"upgradeId":0},{"id":223000,"name":"Sorcerer Boots","itemType":"armor","dur":100,"weight":1.4,"sell":100,"armorType":"legs","armorSet":"Sorcerer","iconId":1120,"defN":12,"defSl":12.5,"defSt":13,"defTh":12,"defM":16,"defF":8,"defL":10,"defP":0,"defT":7,"defB":9,"defC":0,"upgradeId":0},{"id":230000,"name":"Tattered Cloth Hood","itemType":"armor","dur":100,"weight":1.1,"sell":100,"armorType":"head","armorSet":"Tattered Cloth","iconId":1165,"defN":8,"defSl":8,"defSt":8.9,"defTh":8,"defM":9,"defF":12,"defL":6,"defP":0,"defT":23,"defB":9,"defC":1,"upgradeId":0},{"id":231000,"name":"Tattered Cloth Robe","itemType":"armor","dur":100,"weight":2.7,"sell":100,"armorType":"chest","armorSet":"Tattered Cloth","iconId":1166,"defN":21,"defSl":21,"defSt":23.3,"defTh":21,"defM":23,"defF":30,"defL":17,"defP":0,"defT":59,"defB":23,"defC":2,"upgradeId":0},{"id":232000,"name":"Tattered Cloth Manchette","itemType":"armor","dur":100,"weight":1.6,"sell":100,"armorType":"hands","armorSet":"Tattered Cloth","iconId":1167,"defN":12,"defSl":12,"defSt":13.3,"defTh":12,"defM":14,"defF":18,"defL":10,"defP":0,"defT":35,"defB":14,"defC":1,"upgradeId":0},{"id":233000,"name":"Heavy Boots","itemType":"armor","dur":100,"weight":1.6,"sell":100,"armorType":"legs","armorSet":"Tattered Cloth","iconId":1168,"defN":12,"defSl":12,"defSt":13.3,"defTh":12,"defM":14,"defF":18,"defL":10,"defP":0,"defT":35,"defB":14,"defC":1,"upgradeId":0},{"id":240000,"name":"Pharis's Hat","itemType":"armor","dur":100,"weight":1.2,"sell":100,"armorType":"head","armorSet":"Hunter","iconId":1169,"defN":7,"defSl":7,"defSt":7.4,"defTh":7,"defM":5,"defF":7,"defL":6,"defP":0,"defT":5,"defB":6,"defC":0,"upgradeId":0},{"id":241000,"name":"Leather Armor","itemType":"armor","dur":100,"weight":4.7,"sell":100,"armorType":"chest","armorSet":"Hunter","iconId":1170,"defN":24,"defSl":24,"defSt":25.4,"defTh":24,"defM":20,"defF":12,"defL":23,"defP":0,"defT":20,"defB":21,"defC":0,"upgradeId":0},{"id":242000,"name":"Leather Gloves","itemType":"armor","dur":100,"weight":2.8,"sell":100,"armorType":"hands","armorSet":"Hunter","iconId":1171,"defN":12,"defSl":12,"defSt":12.7,"defTh":12,"defM":12,"defF":6,"defL":13,"defP":0,"defT":12,"defB":13,"defC":0,"upgradeId":0},{"id":243000,"name":"Leather Boots","itemType":"armor","dur":100,"weight":2.8,"sell":100,"armorType":"legs","armorSet":"Hunter","iconId":1172,"defN":12,"defSl":12,"defSt":12.7,"defTh":12,"defM":12,"defF":6,"defL":13,"defP":0,"defT":12,"defB":13,"defC":0,"upgradeId":0},{"id":250000,"name":"Painting Guardian Hood","itemType":"armor","dur":100,"weight":0.6,"sell":100,"armorType":"head","armorSet":"Painting Guardian","iconId":1105,"defN":3,"defSl":3,"defSt":3.6,"defTh":3,"defM":31,"defF":11,"defL":8,"defP":0,"defT":30,"defB":12,"defC":6,"upgradeId":100},{"id":251000,"name":"Painting Guardian Robe","itemType":"armor","dur":100,"weight":1.6,"sell":100,"armorType":"chest","armorSet":"Painting Guardian","iconId":1106,"defN":9,"defSl":9,"defSt":10.8,"defTh":9,"defM":34,"defF":29,"defL":21,"defP":0,"defT":78,"defB":32,"defC":16,"upgradeId":100},{"id":252000,"name":"Painting Guardian Gloves","itemType":"armor","dur":100,"weight":0.9,"sell":100,"armorType":"hands","armorSet":"Painting Guardian","iconId":1107,"defN":6,"defSl":6,"defSt":7.2,"defTh":6,"defM":22,"defF":17,"defL":12,"defP":0,"defT":46,"defB":18,"defC":10,"upgradeId":100},{"id":253000,"name":"Painting Guardian Waistcloth","itemType":"armor","dur":100,"weight":4,"sell":100,"armorType":"legs","armorSet":"Painting Guardian","iconId":1108,"defN":22,"defSl":22,"defSt":22.4,"defTh":22,"defM":30,"defF":22,"defL":21,"defP":0,"defT":51,"defB":21,"defC":10,"upgradeId":100},{"id":270000,"name":"Ornstein's Helm","itemType":"armor","dur":100,"weight":5.5,"sell":100,"armorType":"head","armorSet":"Ornstein's","iconId":1121,"defN":32,"defSl":36.2,"defSt":30.4,"defTh":32,"defM":16,"defF":22,"defL":18,"defP":9,"defT":8,"defB":18,"defC":8,"upgradeId":-1,"stRec":-1},{"id":271000,"name":"Ornstein's Armor","itemType":"armor","dur":100,"weight":12,"sell":100,"armorType":"chest","armorSet":"Ornstein's","iconId":1122,"defN":70,"defSl":79.1,"defSt":66.5,"defTh":70,"defM":36,"defF":46,"defL":40,"defP":19,"defT":18,"defB":38,"defC":18,"upgradeId":-1,"stRec":-1},{"id":272000,"name":"Ornstein's Gauntlets","itemType":"armor","dur":100,"weight":4,"sell":100,"armorType":"hands","armorSet":"Ornstein's","iconId":1123,"defN":29,"defSl":32.8,"defSt":27.6,"defTh":29,"defM":12,"defF":16,"defL":14,"defP":6,"defT":6,"defB":12,"defC":6,"upgradeId":-1},{"id":273000,"name":"Ornstein's Leggings","itemType":"armor","dur":100,"weight":7,"sell":100,"armorType":"legs","armorSet":"Ornstein's","iconId":1124,"defN":40,"defSl":45.2,"defSt":38,"defTh":40,"defM":20,"defF":28,"defL":24,"defP":11,"defT":12,"defB":22,"defC":12,"upgradeId":-1,"stRec":-1},{"id":280000,"name":"Eastern Helm","itemType":"armor","dur":100,"weight":4.7,"sell":100,"armorType":"head","armorSet":"Eastern","iconId":1173,"defN":17,"defSl":21.1,"defSt":16.1,"defTh":16.5,"defM":6,"defF":12,"defL":7,"defP":8,"defT":11,"defB":15,"defC":0,"upgradeId":100},{"id":281000,"name":"Eastern Armor","itemType":"armor","dur":100,"weight":12.3,"sell":100,"armorType":"chest","armorSet":"Eastern","iconId":1174,"defN":45,"defSl":55.8,"defSt":42.7,"defTh":43.6,"defM":15,"defF":33,"defL":18,"defP":20,"defT":28,"defB":38,"defC":0,"upgradeId":100,"stRec":-1},{"id":282000,"name":"Eastern Gauntlets","itemType":"armor","dur":100,"weight":1.5,"sell":100,"armorType":"hands","armorSet":"Eastern","iconId":1175,"defN":6,"defSl":7.4,"defSt":5.7,"defTh":5.8,"defM":1,"defF":4,"defL":2,"defP":2,"defT":4,"defB":5,"defC":0,"upgradeId":100},{"id":283000,"name":"Eastern Leggings","itemType":"armor","dur":100,"weight":4,"sell":100,"armorType":"legs","armorSet":"Eastern","iconId":1176,"defN":15,"defSl":18.6,"defSt":14.2,"defTh":14.5,"defM":5,"defF":11,"defL":6,"defP":6,"defT":10,"defB":12,"defC":0,"upgradeId":100},{"id":290000,"name":"Xanthous Crown","itemType":"armor","dur":100,"weight":5,"sell":100,"armorType":"head","armorSet":"Xanthous","iconId":1129,"defN":18,"defSl":18,"defSt":27.7,"defTh":15.3,"defM":15,"defF":3,"defL":8,"defP":0,"defT":11,"defB":8,"defC":35,"upgradeId":100},{"id":291000,"name":"Xanthous Overcoat","itemType":"armor","dur":100,"weight":3.9,"sell":100,"armorType":"chest","armorSet":"Xanthous","iconId":1130,"defN":32,"defSl":32,"defSt":35.8,"defTh":29.1,"defM":37,"defF":7,"defL":23,"defP":0,"defT":29,"defB":22,"defC":0,"upgradeId":100},{"id":292000,"name":"Xanthous Gloves","itemType":"armor","dur":100,"weight":2.3,"sell":100,"armorType":"hands","armorSet":"Xanthous","iconId":1131,"defN":18,"defSl":18,"defSt":20.2,"defTh":16.4,"defM":22,"defF":4,"defL":14,"defP":0,"defT":18,"defB":12,"defC":0,"upgradeId":100},{"id":293000,"name":"Xanthous Waistcloth","itemType":"armor","dur":100,"weight":4,"sell":100,"armorType":"legs","armorSet":"Xanthous","iconId":1132,"defN":32,"defSl":32,"defSt":35.8,"defTh":29.1,"defM":39,"defF":7,"defL":23,"defP":0,"defT":30,"defB":22,"defC":0,"upgradeId":100},{"id":300000,"name":"Thief Mask","itemType":"armor","dur":100,"weight":1.2,"sell":100,"armorType":"head","armorSet":"Black Leather","iconId":1177,"defN":9,"defSl":9,"defSt":9.6,"defTh":9,"defM":8,"defF":5,"defL":6,"defP":0,"defT":12,"defB":9,"defC":0,"upgradeId":0},{"id":301000,"name":"Black Leather Armor","itemType":"armor","dur":100,"weight":3.1,"sell":100,"armorType":"chest","armorSet":"Black Leather","iconId":1178,"defN":23,"defSl":23,"defSt":24.6,"defTh":23,"defM":20,"defF":14,"defL":16,"defP":0,"defT":31,"defB":23,"defC":0,"upgradeId":0},{"id":302000,"name":"Black Leather Gloves","itemType":"armor","dur":100,"weight":1.8,"sell":100,"armorType":"hands","armorSet":"Black Leather","iconId":1179,"defN":13,"defSl":13,"defSt":13.9,"defTh":13,"defM":12,"defF":8,"defL":9,"defP":0,"defT":18,"defB":14,"defC":0,"upgradeId":0},{"id":303000,"name":"Black Leather Boots","itemType":"armor","dur":100,"weight":3,"sell":100,"armorType":"legs","armorSet":"Black Leather","iconId":1180,"defN":12,"defSl":12,"defSt":12.8,"defTh":12,"defM":19,"defF":13,"defL":15,"defP":0,"defT":31,"defB":23,"defC":0,"upgradeId":0},{"id":310000,"name":"Priest's Hat","itemType":"armor","dur":100,"weight":1.2,"sell":100,"armorType":"head","armorSet":"Holy","iconId":1181,"defN":8,"defSl":8,"defSt":9.4,"defTh":8,"defM":9,"defF":5,"defL":7,"defP":0,"defT":8,"defB":9,"defC":0,"upgradeId":0},{"id":311000,"name":"Holy Robe","itemType":"armor","dur":100,"weight":4,"sell":100,"armorType":"chest","armorSet":"Holy","iconId":1182,"defN":22,"defSl":22,"defSt":26,"defTh":22,"defM":23,"defF":14,"defL":19,"defP":0,"defT":20,"defB":24,"defC":0,"upgradeId":0},{"id":312000,"name":"Traveling Gloves","itemType":"armor","dur":100,"weight":0.7,"sell":100,"armorType":"hands","armorSet":"Holy","iconId":1183,"defN":5,"defSl":5,"defSt":5.9,"defTh":5,"defM":5,"defF":3,"defL":4,"defP":0,"defT":4,"defB":5,"defC":0,"upgradeId":0},{"id":313000,"name":"Holy Trousers","itemType":"armor","dur":100,"weight":2,"sell":100,"armorType":"legs","armorSet":"Holy","iconId":1184,"defN":14,"defSl":14,"defSt":17,"defTh":14,"defM":15,"defF":8,"defL":12,"defP":0,"defT":13,"defB":15,"defC":0,"upgradeId":0},{"id":320000,"name":"Black Knight Helm","itemType":"armor","dur":100,"weight":5,"sell":100,"armorType":"head","armorSet":"Black Knight","iconId":1141,"defN":21,"defSl":19.9,"defSt":23.7,"defTh":20.6,"defM":11,"defF":18,"defL":6,"defP":8,"defT":6,"defB":12,"defC":0,"upgradeId":100,"stRec":-1},{"id":321000,"name":"Black Knight Armor","itemType":"armor","dur":100,"weight":13,"sell":100,"armorType":"chest","armorSet":"Black Knight","iconId":1142,"defN":57,"defSl":64.4,"defSt":54.2,"defTh":55.9,"defM":29,"defF":48,"defL":17,"defP":21,"defT":15,"defB":32,"defC":0,"upgradeId":100,"stRec":-1},{"id":322000,"name":"Black Knight Gauntlets","itemType":"armor","dur":100,"weight":6,"sell":100,"armorType":"hands","armorSet":"Black Knight","iconId":1143,"defN":26,"defSl":29.4,"defSt":24.7,"defTh":25.5,"defM":14,"defF":23,"defL":8,"defP":10,"defT":8,"defB":15,"defC":0,"upgradeId":100,"stRec":-1},{"id":323000,"name":"Black Knight Leggings","itemType":"armor","dur":100,"weight":7,"sell":100,"armorType":"legs","armorSet":"Black Knight","iconId":1144,"defN":30,"defSl":33.9,"defSt":28.5,"defTh":29.4,"defM":15,"defF":26,"defL":9,"defP":11,"defT":9,"defB":17,"defC":0,"upgradeId":100,"stRec":-1},{"id":330000,"name":"Crown of Dusk","itemType":"armor","dur":100,"weight":0.4,"sell":1000,"armorType":"head","armorSet":"Antiquated","iconId":1145,"defN":5,"defSl":5,"defSt":5,"defTh":5,"defM":11,"defF":2,"defL":6,"defP":0,"defT":5,"defB":5,"defC":20,"upgradeId":-1},{"id":331000,"name":"Antiquated Dress","itemType":"armor","dur":100,"weight":1,"sell":1000,"armorType":"chest","armorSet":"Antiquated","iconId":1146,"defN":14,"defSl":14,"defSt":14,"defTh":14,"defM":33,"defF":6,"defL":19,"defP":0,"defT":14,"defB":14,"defC":26,"upgradeId":100},{"id":332000,"name":"Antiquated Gloves","itemType":"armor","dur":100,"weight":0.6,"sell":1000,"armorType":"hands","armorSet":"Antiquated","iconId":1147,"defN":8,"defSl":8,"defSt":8,"defTh":8,"defM":19,"defF":3,"defL":11,"defP":0,"defT":8,"defB":8,"defC":16,"upgradeId":100},{"id":333000,"name":"Antiquated Skirt","itemType":"armor","dur":100,"weight":3,"sell":1000,"armorType":"legs","armorSet":"Antiquated","iconId":1148,"defN":15,"defSl":15,"defSt":15,"defTh":15,"defM":35,"defF":17,"defL":21,"defP":0,"defT":20,"defB":20,"defC":51,"upgradeId":100},{"id":340000,"name":"Witch Hat","itemType":"armor","dur":100,"weight":1.1,"sell":1000,"armorType":"head","armorSet":"Witch","iconId":1149,"defN":9,"defSl":9,"defSt":10,"defTh":9,"defM":12,"defF":6,"defL":7,"defP":0,"defT":10,"defB":10,"defC":11,"upgradeId":100},{"id":341000,"name":"Witch Cloak","itemType":"armor","dur":100,"weight":4,"sell":1000,"armorType":"chest","armorSet":"Witch","iconId":1150,"defN":33,"defSl":33,"defSt":37,"defTh":33,"defM":43,"defF":20,"defL":26,"defP":0,"defT":36,"defB":36,"defC":12,"upgradeId":100},{"id":342000,"name":"Witch Gloves","itemType":"armor","dur":100,"weight":1.7,"sell":1000,"armorType":"hands","armorSet":"Witch","iconId":1151,"defN":14,"defSl":14,"defSt":15.5,"defTh":14,"defM":18,"defF":9,"defL":11,"defP":0,"defT":16,"defB":16,"defC":6,"upgradeId":100},{"id":343000,"name":"Witch Skirt","itemType":"armor","dur":100,"weight":2.5,"sell":1000,"armorType":"legs","armorSet":"Witch","iconId":1152,"defN":17,"defSl":17,"defSt":18.9,"defTh":17,"defM":27,"defF":12,"defL":17,"defP":0,"defT":28,"defB":23,"defC":8,"upgradeId":100},{"id":350000,"name":"Elite Knight Helm","itemType":"armor","dur":100,"weight":4.5,"sell":100,"armorType":"head","armorSet":"Elite Knight","iconId":1185,"defN":15,"defSl":17.4,"defSt":14.6,"defTh":15,"defM":7,"defF":8,"defL":6,"defP":8,"defT":6,"defB":9,"defC":0,"upgradeId":0},{"id":351000,"name":"Elite Knight Armor","itemType":"armor","dur":100,"weight":11.7,"sell":100,"armorType":"chest","armorSet":"Elite Knight","iconId":1186,"defN":39,"defSl":45.2,"defSt":37.8,"defTh":39,"defM":17,"defF":18,"defL":15,"defP":20,"defT":16,"defB":23,"defC":0,"upgradeId":0},{"id":352000,"name":"Elite Knight Gauntlets","itemType":"armor","dur":100,"weight":3.7,"sell":100,"armorType":"hands","armorSet":"Elite Knight","iconId":1187,"defN":18,"defSl":20.9,"defSt":17.5,"defTh":18,"defM":7,"defF":8,"defL":5,"defP":6,"defT":5,"defB":7,"defC":0,"upgradeId":0},{"id":353000,"name":"Elite Knight Leggings","itemType":"armor","dur":100,"weight":6.9,"sell":100,"armorType":"legs","armorSet":"Elite Knight","iconId":1188,"defN":23,"defSl":26.7,"defSt":22.3,"defTh":23,"defM":11,"defF":11,"defL":9,"defP":12,"defT":9,"defB":14,"defC":0,"upgradeId":0},{"id":360000,"name":"Wanderer Hood","itemType":"armor","dur":100,"weight":1.4,"sell":100,"armorType":"head","armorSet":"Wanderer","iconId":1193,"defN":9,"defSl":9.6,"defSt":9.6,"defTh":9,"defM":8,"defF":10,"defL":9,"defP":0,"defT":8,"defB":8,"defC":0,"upgradeId":0},{"id":361000,"name":"Wanderer Coat","itemType":"armor","dur":100,"weight":3.5,"sell":100,"armorType":"chest","armorSet":"Wanderer","iconId":1194,"defN":23,"defSl":24.6,"defSt":24.6,"defTh":23,"defM":21,"defF":26,"defL":23,"defP":0,"defT":21,"defB":21,"defC":0,"upgradeId":0},{"id":362000,"name":"Wanderer Manchette","itemType":"armor","dur":100,"weight":2.1,"sell":100,"armorType":"hands","armorSet":"Wanderer","iconId":1195,"defN":14,"defSl":15,"defSt":15,"defTh":14,"defM":12,"defF":15,"defL":13,"defP":0,"defT":13,"defB":13,"defC":0,"upgradeId":0},{"id":363000,"name":"Wanderer Boots","itemType":"armor","dur":100,"weight":2.1,"sell":100,"armorType":"legs","armorSet":"Wanderer","iconId":1196,"defN":14,"defSl":15,"defSt":15,"defTh":14,"defM":12,"defF":15,"defL":13,"defP":0,"defT":13,"defB":13,"defC":0,"upgradeId":0},{"id":380000,"name":"Big Hat","itemType":"armor","dur":100,"weight":3,"sell":100,"armorType":"head","armorSet":"Big Hat's","iconId":1205,"defN":14,"defSl":15.4,"defSt":15.4,"defTh":12.6,"defM":43,"defF":7,"defL":17,"defP":0,"defT":13,"defB":13,"defC":0,"upgradeId":100},{"id":381000,"name":"Sage Robe","itemType":"armor","dur":100,"weight":4,"sell":100,"armorType":"chest","armorSet":"Big Hat's","iconId":1206,"defN":41,"defSl":42.6,"defSt":44.3,"defTh":41,"defM":28,"defF":29,"defL":35,"defP":0,"defT":49,"defB":49,"defC":0,"upgradeId":100},{"id":382000,"name":"Traveling Gloves","itemType":"armor","dur":100,"weight":1.6,"sell":100,"armorType":"hands","armorSet":"Big Hat's","iconId":1207,"defN":12,"defSl":12.5,"defSt":13,"defTh":12,"defM":16,"defF":8,"defL":10,"defP":0,"defT":14,"defB":14,"defC":0,"upgradeId":0},{"id":383000,"name":"Traveling Boots","itemType":"armor","dur":100,"weight":1.6,"sell":100,"armorType":"legs","armorSet":"Big Hat's","iconId":1208,"defN":12,"defSl":12.5,"defSt":13,"defTh":12,"defM":16,"defF":8,"defL":10,"defP":0,"defT":14,"defB":14,"defC":0,"upgradeId":0},{"id":390000,"name":"Knight Helm","itemType":"armor","dur":100,"weight":4.2,"sell":100,"armorType":"head","armorSet":"Knight","iconId":1209,"defN":14,"defSl":16.2,"defSt":13.3,"defTh":13.7,"defM":6,"defF":8,"defL":5,"defP":8,"defT":6,"defB":9,"defC":0,"upgradeId":0},{"id":391000,"name":"Knight Armor","itemType":"armor","dur":100,"weight":10.9,"sell":100,"armorType":"chest","armorSet":"Knight","iconId":1210,"defN":37,"defSl":43,"defSt":35,"defTh":36,"defM":16,"defF":18,"defL":13,"defP":20,"defT":16,"defB":23,"defC":0,"upgradeId":0},{"id":392000,"name":"Knight Gauntlets","itemType":"armor","dur":100,"weight":3.5,"sell":100,"armorType":"hands","armorSet":"Knight","iconId":1211,"defN":17,"defSl":19.7,"defSt":16.1,"defTh":16.7,"defM":7,"defF":8,"defL":4,"defP":6,"defT":5,"defB":8,"defC":0,"upgradeId":0},{"id":393000,"name":"Knight Leggings","itemType":"armor","dur":100,"weight":6.4,"sell":100,"armorType":"legs","armorSet":"Knight","iconId":1241,"defN":22,"defSl":25.5,"defSt":20.9,"defTh":21.6,"defM":10,"defF":11,"defL":8,"defP":12,"defT":9,"defB":14,"defC":0,"upgradeId":0},{"id":400000,"name":"Dingy Hood","itemType":"armor","dur":100,"weight":0.8,"sell":1000,"armorType":"head","armorSet":"Dingy","iconId":1213,"defN":6,"defSl":6,"defSt":7.5,"defTh":6,"defM":8,"defF":5,"defL":6,"defP":0,"defT":7,"defB":9,"defC":9,"upgradeId":0},{"id":401000,"name":"Dingy Robe","itemType":"armor","dur":100,"weight":3,"sell":1000,"armorType":"chest","armorSet":"Dingy","iconId":1214,"defN":23,"defSl":23,"defSt":28.7,"defTh":23,"defM":33,"defF":19,"defL":25,"defP":0,"defT":26,"defB":35,"defC":35,"upgradeId":0},{"id":402000,"name":"Dingy Gloves","itemType":"armor","dur":100,"weight":1.2,"sell":1000,"armorType":"hands","armorSet":"Dingy","iconId":1215,"defN":9,"defSl":9,"defSt":11.3,"defTh":9,"defM":13,"defF":8,"defL":10,"defP":0,"defT":10,"defB":14,"defC":14,"upgradeId":0},{"id":403000,"name":"Blood-Stained Skirt","itemType":"armor","dur":100,"weight":2.5,"sell":1000,"armorType":"legs","armorSet":"Dingy","iconId":1216,"defN":13,"defSl":13,"defSt":16.3,"defTh":13,"defM":27,"defF":16,"defL":21,"defP":0,"defT":22,"defB":29,"defC":29,"upgradeId":0},{"id":410000,"name":"Maiden Hood","itemType":"armor","dur":100,"weight":0.8,"sell":1000,"armorType":"head","armorSet":"Maiden","iconId":1217,"defN":7,"defSl":7,"defSt":8.2,"defTh":7,"defM":8,"defF":5,"defL":6,"defP":0,"defT":7,"defB":9,"defC":3,"upgradeId":0},{"id":411000,"name":"Maiden Robe","itemType":"armor","dur":100,"weight":2,"sell":1000,"armorType":"chest","armorSet":"Maiden","iconId":1218,"defN":19,"defSl":19,"defSt":22.2,"defTh":19,"defM":22,"defF":13,"defL":17,"defP":0,"defT":18,"defB":23,"defC":8,"upgradeId":0},{"id":412000,"name":"Maiden Gloves","itemType":"armor","dur":100,"weight":1.2,"sell":1000,"armorType":"hands","armorSet":"Maiden","iconId":1219,"defN":11,"defSl":11,"defSt":12.9,"defTh":11,"defM":13,"defF":8,"defL":10,"defP":0,"defT":10,"defB":14,"defC":5,"upgradeId":0},{"id":413000,"name":"Maiden Skirt","itemType":"armor","dur":100,"weight":2.5,"sell":1000,"armorType":"legs","armorSet":"Maiden","iconId":1220,"defN":14,"defSl":14,"defSt":16.4,"defTh":14,"defM":27,"defF":16,"defL":21,"defP":0,"defT":22,"defB":29,"defC":10,"upgradeId":0},{"id":420000,"name":"Silver Knight Helm","itemType":"armor","dur":100,"weight":4.8,"sell":100,"armorType":"head","armorSet":"Silver Knight","iconId":1221,"defN":21,"defSl":24.1,"defSt":19.7,"defTh":20.6,"defM":10,"defF":11,"defL":14,"defP":8,"defT":5,"defB":9,"defC":1,"upgradeId":100},{"id":421000,"name":"Silver Knight Armor","itemType":"armor","dur":100,"weight":12,"sell":100,"armorType":"chest","armorSet":"Silver Knight","iconId":1222,"defN":52,"defSl":59.8,"defSt":48.9,"defTh":51,"defM":26,"defF":29,"defL":34,"defP":19,"defT":12,"defB":24,"defC":2,"upgradeId":100},{"id":422000,"name":"Silver Knight Gauntlets","itemType":"armor","dur":100,"weight":5.5,"sell":100,"armorType":"hands","armorSet":"Silver Knight","iconId":1223,"defN":25,"defSl":28.7,"defSt":23.5,"defTh":24.5,"defM":12,"defF":14,"defL":16,"defP":9,"defT":6,"defB":11,"defC":1,"upgradeId":100},{"id":423000,"name":"Silver Knight Leggings","itemType":"armor","dur":100,"weight":6.5,"sell":100,"armorType":"legs","armorSet":"Silver Knight","iconId":1224,"defN":28,"defSl":32.2,"defSt":26.3,"defTh":27.4,"defM":15,"defF":16,"defL":19,"defP":11,"defT":7,"defB":14,"defC":1,"upgradeId":100},{"id":440000,"name":"Havel's Helm","itemType":"armor","dur":100,"weight":7.5,"sell":100,"armorType":"head","armorSet":"Havel's","iconId":1229,"defN":36,"defSl":41.4,"defSt":30.6,"defTh":36,"defM":22,"defF":22,"defL":18,"defP":18,"defT":4,"defB":18,"defC":9,"upgradeId":-1,"stRec":-1},{"id":441000,"name":"Havel's Armor","itemType":"armor","dur":100,"weight":19.5,"sell":100,"armorType":"chest","armorSet":"Havel's","iconId":1230,"defN":92,"defSl":105.8,"defSt":78.2,"defTh":92,"defM":56,"defF":54,"defL":49,"defP":47,"defT":11,"defB":45,"defC":22,"upgradeId":-1,"stRec":-2},{"id":442000,"name":"Havel's Gauntlets","itemType":"armor","dur":100,"weight":11.5,"sell":100,"armorType":"hands","armorSet":"Havel's","iconId":1231,"defN":54,"defSl":62.1,"defSt":45.9,"defTh":54,"defM":32,"defF":32,"defL":29,"defP":28,"defT":5,"defB":27,"defC":13,"upgradeId":-1,"stRec":-1},{"id":443000,"name":"Havel's Leggings","itemType":"armor","dur":100,"weight":11.5,"sell":100,"armorType":"legs","armorSet":"Havel's","iconId":1232,"defN":54,"defSl":62.1,"defSt":45.9,"defTh":54,"defM":32,"defF":32,"defL":29,"defP":28,"defT":5,"defB":27,"defC":13,"upgradeId":-1,"stRec":-1},{"id":450000,"name":"Brass Helm","itemType":"armor","dur":100,"weight":5.1,"sell":100,"armorType":"head","armorSet":"Brass","iconId":1237,"defN":22,"defSl":24.9,"defSt":21.1,"defTh":22,"defM":12,"defF":11,"defL":11,"defP":8,"defT":9,"defB":11,"defC":6,"upgradeId":100},{"id":451000,"name":"Brass Armor","itemType":"armor","dur":100,"weight":10.9,"sell":100,"armorType":"chest","armorSet":"Brass","iconId":1238,"defN":48,"defSl":54.2,"defSt":46.1,"defTh":48,"defM":27,"defF":25,"defL":25,"defP":16,"defT":20,"defB":24,"defC":11,"upgradeId":100},{"id":452000,"name":"Brass Gauntlets","itemType":"armor","dur":100,"weight":5.4,"sell":100,"armorType":"hands","armorSet":"Brass","iconId":1239,"defN":24,"defSl":27.1,"defSt":23,"defTh":24,"defM":14,"defF":12,"defL":12,"defP":8,"defT":10,"defB":12,"defC":6,"upgradeId":100},{"id":453000,"name":"Brass Leggings","itemType":"armor","dur":100,"weight":6.4,"sell":100,"armorType":"legs","armorSet":"Brass","iconId":1240,"defN":26,"defSl":29.4,"defSt":25,"defTh":26,"defM":16,"defF":15,"defL":15,"defP":9,"defT":12,"defB":14,"defC":7,"upgradeId":100},{"id":460000,"name":"Gold-Hemmed Black Hood","itemType":"armor","dur":100,"weight":1.4,"sell":1000,"armorType":"head","armorSet":"Gold-Hemmed Black","iconId":1242,"defN":11,"defSl":11,"defSt":11.8,"defTh":11,"defM":15,"defF":22,"defL":8,"defP":0,"defT":36,"defB":16,"defC":0,"upgradeId":-1},{"id":461000,"name":"Gold-Hemmed Black Cloak","itemType":"armor","dur":100,"weight":3.5,"sell":1000,"armorType":"chest","armorSet":"Gold-Hemmed Black","iconId":1243,"defN":31,"defSl":31,"defSt":33.2,"defTh":31,"defM":38,"defF":58,"defL":21,"defP":0,"defT":94,"defB":40,"defC":0,"upgradeId":-1},{"id":462000,"name":"Gold-Hemmed Black Gloves","itemType":"armor","dur":100,"weight":1.2,"sell":1000,"armorType":"hands","armorSet":"Gold-Hemmed Black","iconId":1244,"defN":12,"defSl":12,"defSt":12.8,"defTh":12,"defM":13,"defF":24,"defL":8,"defP":0,"defT":32,"defB":14,"defC":0,"upgradeId":-1},{"id":463000,"name":"Gold-Hemmed Black Skirt","itemType":"armor","dur":100,"weight":3,"sell":1000,"armorType":"legs","armorSet":"Gold-Hemmed Black","iconId":1245,"defN":23,"defSl":23,"defSt":24.6,"defTh":23,"defM":27,"defF":49,"defL":17,"defP":0,"defT":78,"defB":32,"defC":0,"upgradeId":-1},{"id":470000,"name":"Golem Helm","itemType":"armor","dur":100,"weight":6.3,"sell":100,"armorType":"head","armorSet":"Golem","iconId":1246,"defN":35,"defSl":40.9,"defSt":32.2,"defTh":35,"defM":17,"defF":16,"defL":6,"defP":13,"defT":12,"defB":17,"defC":0,"upgradeId":-1,"stRec":-1},{"id":471000,"name":"Golem Armor","itemType":"armor","dur":100,"weight":16.4,"sell":100,"armorType":"chest","armorSet":"Golem","iconId":1247,"defN":91,"defSl":106.5,"defSt":83.7,"defTh":91,"defM":45,"defF":41,"defL":17,"defP":33,"defT":31,"defB":45,"defC":0,"upgradeId":-1,"stRec":-2},{"id":472000,"name":"Golem Gauntlets","itemType":"armor","dur":100,"weight":9.7,"sell":100,"armorType":"hands","armorSet":"Golem","iconId":1248,"defN":54,"defSl":63.2,"defSt":49.7,"defTh":54,"defM":25,"defF":33,"defL":10,"defP":20,"defT":17,"defB":27,"defC":0,"upgradeId":-1,"stRec":-1},{"id":473000,"name":"Golem Leggings","itemType":"armor","dur":100,"weight":9.7,"sell":100,"armorType":"legs","armorSet":"Golem","iconId":1249,"defN":54,"defSl":63.2,"defSt":49.7,"defTh":54,"defM":25,"defF":33,"defL":10,"defP":20,"defT":17,"defB":27,"defC":0,"upgradeId":-1,"stRec":-1},{"id":480000,"name":"Hollow Soldier Helm","itemType":"armor","dur":100,"weight":3,"sell":100,"armorType":"head","armorSet":"Hollow Soldier","iconId":1250,"defN":10,"defSl":11.1,"defSt":10,"defTh":8.8,"defM":6,"defF":6,"defL":4,"defP":5,"defT":5,"defB":7,"defC":0,"upgradeId":0},{"id":481000,"name":"Hollow Soldier Armor","itemType":"armor","dur":100,"weight":7.8,"sell":100,"armorType":"chest","armorSet":"Hollow Soldier","iconId":1251,"defN":26,"defSl":28.9,"defSt":26,"defTh":22.9,"defM":16,"defF":17,"defL":10,"defP":12,"defT":13,"defB":18,"defC":0,"upgradeId":0},{"id":483000,"name":"Hollow Soldier Waistcloth","itemType":"armor","dur":100,"weight":1.5,"sell":100,"armorType":"legs","armorSet":"Hollow Soldier","iconId":1253,"defN":13,"defSl":14.4,"defSt":13,"defTh":11.4,"defM":8,"defF":8,"defL":6,"defP":7,"defT":6,"defB":10,"defC":0,"upgradeId":0},{"id":490000,"name":"Steel Helm","itemType":"armor","dur":100,"weight":5.4,"sell":100,"armorType":"head","armorSet":"Steel Set","iconId":1254,"defN":16,"defSl":18.4,"defSt":15,"defTh":16,"defM":8,"defF":8,"defL":5,"defP":9,"defT":6,"defB":9,"defC":0,"upgradeId":0,"stRec":-1},{"id":491000,"name":"Steel Armor","itemType":"armor","dur":100,"weight":14,"sell":100,"armorType":"chest","armorSet":"Steel Set","iconId":1255,"defN":42,"defSl":48.3,"defSt":39.5,"defTh":42,"defM":22,"defF":21,"defL":13,"defP":23,"defT":16,"defB":23,"defC":0,"upgradeId":0,"stRec":-1},{"id":492000,"name":"Steel Gauntlets","itemType":"armor","dur":100,"weight":8.3,"sell":100,"armorType":"hands","armorSet":"Steel Set","iconId":1256,"defN":25,"defSl":28.8,"defSt":23.5,"defTh":25,"defM":13,"defF":12,"defL":8,"defP":14,"defT":9,"defB":14,"defC":0,"upgradeId":0,"stRec":-1},{"id":493000,"name":"Steel Leggings","itemType":"armor","dur":100,"weight":8.3,"sell":100,"armorType":"legs","armorSet":"Steel Set","iconId":1257,"defN":25,"defSl":28.8,"defSt":23.5,"defTh":25,"defM":13,"defF":12,"defL":8,"defP":14,"defT":9,"defB":14,"defC":0,"upgradeId":0,"stRec":-1},{"id":500000,"name":"Hollow Thief's Hood","itemType":"armor","dur":100,"weight":1.1,"sell":100,"armorType":"head","armorSet":"Hollow Thief's","iconId":1258,"defN":8,"defSl":8,"defSt":8.7,"defTh":8.3,"defM":8,"defF":5,"defL":7,"defP":0,"defT":11,"defB":6,"defC":0,"upgradeId":0},{"id":501000,"name":"Hollow Thief's Leather Armor","itemType":"armor","dur":100,"weight":2.8,"sell":100,"armorType":"chest","armorSet":"Hollow Thief's","iconId":1259,"defN":21,"defSl":21,"defSt":22.9,"defTh":21.8,"defM":20,"defF":13,"defL":18,"defP":0,"defT":29,"defB":15,"defC":0,"upgradeId":0},{"id":503000,"name":"Hollow Thief's Tights","itemType":"armor","dur":100,"weight":1.7,"sell":100,"armorType":"legs","armorSet":"Hollow Thief's","iconId":1261,"defN":12,"defSl":12,"defSt":13.1,"defTh":12.5,"defM":11,"defF":8,"defL":10,"defP":0,"defT":17,"defB":9,"defC":0,"upgradeId":0},{"id":510000,"name":"Balder Helm","itemType":"armor","dur":100,"weight":4.2,"sell":100,"armorType":"head","armorSet":"Balder","iconId":1262,"defN":14,"defSl":17.1,"defSt":13.7,"defTh":13.4,"defM":6,"defF":8,"defL":6,"defP":6,"defT":6,"defB":8,"defC":0,"upgradeId":0},{"id":511000,"name":"Balder Armor","itemType":"armor","dur":100,"weight":10.9,"sell":100,"armorType":"chest","armorSet":"Balder","iconId":1263,"defN":37,"defSl":45.1,"defSt":36.3,"defTh":35.5,"defM":15,"defF":18,"defL":15,"defP":16,"defT":16,"defB":20,"defC":0,"upgradeId":0},{"id":512000,"name":"Balder Gauntlets","itemType":"armor","dur":100,"weight":3.5,"sell":100,"armorType":"hands","armorSet":"Balder","iconId":1264,"defN":17,"defSl":20.7,"defSt":16.7,"defTh":16.3,"defM":7,"defF":8,"defL":5,"defP":5,"defT":5,"defB":6,"defC":0,"upgradeId":0},{"id":513000,"name":"Balder Leggings","itemType":"armor","dur":100,"weight":6.4,"sell":100,"armorType":"legs","armorSet":"Balder","iconId":1265,"defN":22,"defSl":26.8,"defSt":21.6,"defTh":21.1,"defM":12,"defF":14,"defL":9,"defP":9,"defT":9,"defB":12,"defC":0,"upgradeId":0},{"id":520000,"name":"Hollow Warrior Helm","itemType":"armor","dur":100,"weight":2.6,"sell":100,"armorType":"head","armorSet":"Hollow Warrior","iconId":1266,"defN":10,"defSl":10.3,"defSt":9.7,"defTh":9.5,"defM":6,"defF":5,"defL":6,"defP":3,"defT":5,"defB":5,"defC":0,"upgradeId":0},{"id":521000,"name":"Hollow Warrior Armor","itemType":"armor","dur":100,"weight":6.6,"sell":100,"armorType":"chest","armorSet":"Hollow Warrior","iconId":1267,"defN":24,"defSl":24.7,"defSt":23.3,"defTh":22.8,"defM":16,"defF":12,"defL":17,"defP":8,"defT":13,"defB":13,"defC":0,"upgradeId":0},{"id":523000,"name":"Hollow Warrior Waistcloth","itemType":"armor","dur":100,"weight":1.4,"sell":100,"armorType":"legs","armorSet":"Hollow Warrior","iconId":1269,"defN":13,"defSl":13.4,"defSt":12.6,"defTh":12.3,"defM":8,"defF":6,"defL":8,"defP":5,"defT":6,"defB":6,"defC":0,"upgradeId":0},{"id":530000,"name":"Giant Helm","itemType":"armor","dur":100,"weight":6.3,"sell":100,"armorType":"head","armorSet":"Giant","iconId":1008,"defN":27,"defSl":30.5,"defSt":24.8,"defTh":27,"defM":13,"defF":19,"defL":13,"defP":14,"defT":8,"defB":13,"defC":0,"upgradeId":100,"stRec":-1},{"id":531000,"name":"Giant Armor","itemType":"armor","dur":100,"weight":16.4,"sell":100,"armorType":"chest","armorSet":"Giant","iconId":1009,"defN":72,"defSl":81.4,"defSt":66.2,"defTh":72,"defM":32,"defF":48,"defL":33,"defP":35,"defT":19,"defB":32,"defC":0,"upgradeId":100,"stRec":-2},{"id":532000,"name":"Giant Gauntlets","itemType":"armor","dur":100,"weight":9.7,"sell":100,"armorType":"hands","armorSet":"Giant","iconId":1010,"defN":41,"defSl":46.3,"defSt":37.7,"defTh":41,"defM":19,"defF":29,"defL":19,"defP":21,"defT":11,"defB":19,"defC":0,"upgradeId":100,"stRec":-1},{"id":533000,"name":"Giant Leggings","itemType":"armor","dur":100,"weight":9.7,"sell":100,"armorType":"legs","armorSet":"Giant","iconId":1011,"defN":41,"defSl":46.3,"defSt":37.7,"defTh":41,"defM":19,"defF":29,"defL":19,"defP":21,"defT":11,"defB":19,"defC":0,"upgradeId":100,"stRec":-1},{"id":540000,"name":"Crown of the Dark Sun","itemType":"armor","dur":100,"weight":3,"sell":1000,"armorType":"head","armorSet":"Moonlight","iconId":1109,"defN":12,"defSl":12,"defSt":12,"defTh":12,"defM":12,"defF":6,"defL":6,"defP":0,"defT":9,"defB":9,"defC":12,"upgradeId":-1},{"id":541000,"name":"Moonlight Robe","itemType":"armor","dur":100,"weight":3.1,"sell":1000,"armorType":"chest","armorSet":"Moonlight","iconId":1110,"defN":20,"defSl":20,"defSt":20,"defTh":20,"defM":31,"defF":17,"defL":17,"defP":0,"defT":23,"defB":23,"defC":31,"upgradeId":-1},{"id":542000,"name":"Moonlight Gloves","itemType":"armor","dur":100,"weight":0.5,"sell":1000,"armorType":"hands","armorSet":"Moonlight","iconId":1111,"defN":3,"defSl":3,"defSt":3,"defTh":3,"defM":5,"defF":3,"defL":3,"defP":0,"defT":4,"defB":4,"defC":5,"upgradeId":-1},{"id":543000,"name":"Moonlight Waistcloth","itemType":"armor","dur":100,"weight":1.8,"sell":1000,"armorType":"legs","armorSet":"Moonlight","iconId":1112,"defN":12,"defSl":12,"defSt":12,"defTh":12,"defM":18,"defF":10,"defL":10,"defP":0,"defT":14,"defB":14,"defC":18,"upgradeId":-1},{"id":550000,"name":"Crown of the Great Lord","itemType":"armor","dur":100,"weight":3,"sell":10000,"armorType":"head","armorSet":"Great Lord","iconId":1225,"defN":16,"defSl":18.4,"defSt":17.3,"defTh":14.7,"defM":16,"defF":21,"defL":21,"defP":0,"defT":18,"defB":15,"defC":20,"upgradeId":-1},{"id":551000,"name":"Robe of the Great Lord","itemType":"armor","dur":100,"weight":6,"sell":1000,"armorType":"chest","armorSet":"Great Lord","iconId":1226,"defN":32,"defSl":37,"defSt":35,"defTh":29,"defM":32,"defF":41,"defL":41,"defP":0,"defT":15,"defB":30,"defC":40,"upgradeId":-1},{"id":552000,"name":"Bracelet of the Great Lord","itemType":"armor","dur":100,"weight":2.8,"sell":1000,"armorType":"hands","armorSet":"Great Lord","iconId":1227,"defN":15,"defSl":17.3,"defSt":16.2,"defTh":13.8,"defM":15,"defF":19,"defL":19,"defP":0,"defT":7,"defB":14,"defC":18,"upgradeId":-1},{"id":553000,"name":"Anklet of the Great Lord","itemType":"armor","dur":100,"weight":2.8,"sell":1000,"armorType":"legs","armorSet":"Great Lord","iconId":1228,"defN":15,"defSl":17.3,"defSt":16.2,"defTh":13.8,"defM":15,"defF":19,"defL":19,"defP":0,"defT":7,"defB":14,"defC":18,"upgradeId":-1},{"id":560000,"name":"Sack","itemType":"armor","dur":100,"weight":0.6,"sell":100,"armorType":"head","armorSet":"","iconId":1270,"defN":6,"defSl":6,"defSt":10,"defTh":5,"defM":6,"defF":8,"defL":4,"defP":0,"defT":10,"defB":12,"defC":0,"upgradeId":0},{"id":570000,"name":"Symbol of Avarice","itemType":"armor","dur":100,"weight":10,"sell":3000,"armorType":"head","armorSet":"","iconId":1271,"defN":21,"defSl":21,"defSt":10.9,"defTh":21,"defM":8,"defF":2,"defL":2,"defP":15,"defT":0,"defB":10,"defC":0,"upgradeId":-1,"stRec":-1},{"id":580000,"name":"Royal Helm","itemType":"armor","dur":100,"weight":4.5,"sell":3000,"armorType":"head","armorSet":"","iconId":1272,"defN":16,"defSl":16,"defSt":13.9,"defTh":16,"defM":10,"defF":10,"defL":6,"defP":8,"defT":12,"defB":16,"defC":0,"upgradeId":0},{"id":590000,"name":"Mask of the Father","itemType":"armor","dur":100,"weight":1.2,"sell":100,"armorType":"head","armorSet":"","iconId":1273,"defN":6,"defSl":6,"defSt":6,"defTh":6,"defM":10,"defF":6,"defL":8,"defP":0,"defT":0,"defB":6,"defC":0,"upgradeId":-1},{"id":600000,"name":"Mask of the Mother","itemType":"armor","dur":100,"weight":1.2,"sell":100,"armorType":"head","armorSet":"","iconId":1274,"defN":6,"defSl":6,"defSt":6,"defTh":6,"defM":12,"defF":6,"defL":8,"defP":0,"defT":0,"defB":10,"defC":0,"upgradeId":-1},{"id":610000,"name":"Mask of the Child","itemType":"armor","dur":100,"weight":1.2,"sell":100,"armorType":"head","armorSet":"","iconId":1275,"defN":6,"defSl":6,"defSt":6,"defTh":6,"defM":10,"defF":8,"defL":10,"defP":0,"defT":0,"defB":6,"defC":0,"upgradeId":-1,"stRec":10},{"id":620000,"name":"Fang Boar Helm","itemType":"armor","dur":100,"weight":8,"sell":1000,"armorType":"head","armorSet":"","iconId":1276,"defN":26,"defSl":31.2,"defSt":23.4,"defTh":26,"defM":5,"defF":4,"defL":4,"defP":12,"defT":8,"defB":13,"defC":0,"upgradeId":100,"stRec":-1},{"id":630000,"name":"Gargoyle Helm","itemType":"armor","dur":100,"weight":3.5,"sell":100,"armorType":"head","armorSet":"","iconId":1277,"defN":15,"defSl":19.1,"defSt":12.3,"defTh":13.7,"defM":15,"defF":15,"defL":15,"defP":8,"defT":19,"defB":22,"defC":0,"upgradeId":100},{"id":640000,"name":"Black Sorcerer Hat","itemType":"armor","dur":100,"weight":0.7,"sell":100,"armorType":"head","armorSet":"Black Sorcerer","iconId":1282,"defN":5,"defSl":5.5,"defSt":5.1,"defTh":5,"defM":11,"defF":8,"defL":8,"defP":0,"defT":12,"defB":12,"defC":2,"upgradeId":0},{"id":641000,"name":"Black Sorcerer Cloak","itemType":"armor","dur":100,"weight":1.8,"sell":100,"armorType":"chest","armorSet":"Black Sorcerer","iconId":1283,"defN":13,"defSl":14.2,"defSt":13.4,"defTh":13,"defM":28,"defF":21,"defL":21,"defP":0,"defT":31,"defB":31,"defC":4,"upgradeId":0},{"id":642000,"name":"Black Sorcerer Gauntlets","itemType":"armor","dur":100,"weight":1,"sell":100,"armorType":"hands","armorSet":"Black Sorcerer","iconId":1284,"defN":8,"defSl":8.7,"defSt":8.2,"defTh":8,"defM":17,"defF":12,"defL":12,"defP":0,"defT":18,"defB":18,"defC":2,"upgradeId":0},{"id":643000,"name":"Black Sorcerer Boots","itemType":"armor","dur":100,"weight":1,"sell":100,"armorType":"legs","armorSet":"Black Sorcerer","iconId":1285,"defN":8,"defSl":8.7,"defSt":8.2,"defTh":8,"defM":17,"defF":12,"defL":12,"defP":0,"defT":18,"defB":18,"defC":2,"upgradeId":0},{"id":650000,"name":"Elite Cleric Helm","itemType":"armor","dur":100,"weight":5.1,"sell":100,"armorType":"head","armorSet":"Elite Cleric","iconId":1290,"defN":16,"defSl":18.2,"defSt":16,"defTh":16,"defM":9,"defF":8,"defL":6,"defP":8,"defT":6,"defB":9,"defC":0,"upgradeId":0,"stRec":-1},{"id":651000,"name":"Elite Cleric Armor","itemType":"armor","dur":100,"weight":13.3,"sell":100,"armorType":"chest","armorSet":"Elite Cleric","iconId":1291,"defN":41,"defSl":46.7,"defSt":41,"defTh":41,"defM":23,"defF":21,"defL":15,"defP":23,"defT":16,"defB":23,"defC":0,"upgradeId":0,"stRec":-1},{"id":652000,"name":"Elite Cleric Gauntlets","itemType":"armor","dur":100,"weight":7.8,"sell":100,"armorType":"hands","armorSet":"Elite Cleric","iconId":1292,"defN":24,"defSl":27.4,"defSt":24,"defTh":24,"defM":13,"defF":12,"defL":9,"defP":14,"defT":9,"defB":14,"defC":0,"upgradeId":0,"stRec":-1},{"id":653000,"name":"Elite Cleric Leggings","itemType":"armor","dur":100,"weight":7.8,"sell":100,"armorType":"legs","armorSet":"Elite Cleric","iconId":1293,"defN":24,"defSl":27.4,"defSt":24,"defTh":24,"defM":13,"defF":12,"defL":9,"defP":14,"defT":9,"defB":14,"defC":0,"upgradeId":0,"stRec":-1},{"id":660000,"name":"Helm of Artorias","itemType":"armor","dur":100,"weight":4.2,"sell":100,"armorType":"head","armorSet":"Artorias","iconId":1294,"defN":18,"defSl":20.7,"defSt":16.2,"defTh":18.9,"defM":9,"defF":19,"defL":9,"defP":6,"defT":9,"defB":9,"defC":9,"upgradeId":100},{"id":661000,"name":"Armor of Artorias","itemType":"armor","dur":100,"weight":10.5,"sell":100,"armorType":"chest","armorSet":"Artorias","iconId":1295,"defN":42,"defSl":48.3,"defSt":37.8,"defTh":44.1,"defM":22,"defF":46,"defL":22,"defP":15,"defT":22,"defB":22,"defC":20,"upgradeId":100},{"id":662000,"name":"Gauntlets of Artorias","itemType":"armor","dur":100,"weight":4.6,"sell":100,"armorType":"hands","armorSet":"Artorias","iconId":1296,"defN":20,"defSl":23,"defSt":18,"defTh":21,"defM":10,"defF":21,"defL":10,"defP":7,"defT":10,"defB":10,"defC":9,"upgradeId":100},{"id":663000,"name":"Leggings of Artorias","itemType":"armor","dur":100,"weight":5.5,"sell":100,"armorType":"legs","armorSet":"Artorias","iconId":1297,"defN":23,"defSl":26.4,"defSt":20.7,"defTh":24.1,"defM":11,"defF":24,"defL":11,"defP":9,"defT":11,"defB":11,"defC":10,"upgradeId":100},{"id":670000,"name":"Porcelain Mask","itemType":"armor","dur":100,"weight":2.5,"sell":100,"armorType":"head","armorSet":"Lord's Blade","iconId":1298,"defN":13,"defSl":13.6,"defSt":13,"defTh":14.3,"defM":10,"defF":12,"defL":8,"defP":3,"defT":19,"defB":11,"defC":11,"upgradeId":100},{"id":671000,"name":"Lord's Blade Robe","itemType":"armor","dur":100,"weight":6.4,"sell":100,"armorType":"chest","armorSet":"Lord's Blade","iconId":1299,"defN":34,"defSl":35.7,"defSt":34,"defTh":37.4,"defM":26,"defF":32,"defL":20,"defP":8,"defT":49,"defB":28,"defC":25,"upgradeId":100},{"id":672000,"name":"Lord's Blade Gloves","itemType":"armor","dur":100,"weight":2.8,"sell":100,"armorType":"hands","armorSet":"Lord's Blade","iconId":1300,"defN":15,"defSl":15.7,"defSt":15,"defTh":16.5,"defM":11,"defF":14,"defL":9,"defP":3,"defT":22,"defB":12,"defC":11,"upgradeId":100},{"id":673000,"name":"Lord's Blade Waistcloth","itemType":"armor","dur":100,"weight":5,"sell":100,"armorType":"legs","armorSet":"Lord's Blade","iconId":1301,"defN":27,"defSl":28.4,"defSt":27,"defTh":29.7,"defM":20,"defF":25,"defL":16,"defP":6,"defT":38,"defB":22,"defC":20,"upgradeId":100},{"id":680000,"name":"Gough's Helm","itemType":"armor","dur":100,"weight":6.5,"sell":100,"armorType":"head","armorSet":"Gough's","iconId":1302,"defN":25,"defSl":26.2,"defSt":25,"defTh":23.8,"defM":14,"defF":21,"defL":11,"defP":9,"defT":6,"defB":11,"defC":0,"upgradeId":100,"stRec":-1},{"id":681000,"name":"Gough's Armor","itemType":"armor","dur":100,"weight":13,"sell":100,"armorType":"chest","armorSet":"Gough's","iconId":1303,"defN":50,"defSl":52.5,"defSt":50,"defTh":47.5,"defM":28,"defF":41,"defL":21,"defP":19,"defT":12,"defB":21,"defC":0,"upgradeId":100,"stRec":-1},{"id":682000,"name":"Gough's Gauntlets","itemType":"armor","dur":100,"weight":7,"sell":100,"armorType":"hands","armorSet":"Gough's","iconId":1304,"defN":27,"defSl":28.3,"defSt":27,"defTh":25.6,"defM":15,"defF":22,"defL":11,"defP":12,"defT":6,"defB":11,"defC":0,"upgradeId":100,"stRec":-1},{"id":683000,"name":"Gough's Leggings","itemType":"armor","dur":100,"weight":8,"sell":100,"armorType":"legs","armorSet":"Gough's","iconId":1305,"defN":31,"defSl":32.5,"defSt":31,"defTh":29.4,"defM":17,"defF":25,"defL":13,"defP":13,"defT":7,"defB":13,"defC":0,"upgradeId":100,"stRec":-1},{"id":690000,"name":"Guardian Helm","itemType":"armor","dur":100,"weight":7.2,"sell":100,"armorType":"head","armorSet":"Guardian","iconId":1306,"defN":41,"defSl":47.1,"defSt":38.5,"defTh":41,"defM":23,"defF":19,"defL":23,"defP":15,"defT":6,"defB":17,"defC":0,"upgradeId":-1,"stRec":-1},{"id":691000,"name":"Guardian Armor","itemType":"armor","dur":100,"weight":17,"sell":100,"armorType":"chest","armorSet":"Guardian","iconId":1307,"defN":86,"defSl":98.9,"defSt":80.8,"defTh":86,"defM":50,"defF":42,"defL":50,"defP":37,"defT":14,"defB":42,"defC":0,"upgradeId":-1,"stRec":-2},{"id":692000,"name":"Guardian Gauntlets","itemType":"armor","dur":100,"weight":10.4,"sell":100,"armorType":"hands","armorSet":"Guardian","iconId":1308,"defN":54,"defSl":62.1,"defSt":50.8,"defTh":54,"defM":33,"defF":27,"defL":33,"defP":23,"defT":10,"defB":27,"defC":0,"upgradeId":-1,"stRec":-1},{"id":693000,"name":"Guardian Leggings","itemType":"armor","dur":100,"weight":10.4,"sell":100,"armorType":"legs","armorSet":"Guardian","iconId":1309,"defN":54,"defSl":62.1,"defSt":50.8,"defTh":54,"defM":33,"defF":27,"defL":33,"defP":23,"defT":10,"defB":27,"defC":0,"upgradeId":-1,"stRec":-1},{"id":700000,"name":"Snickering Top Hat","itemType":"armor","dur":100,"weight":2,"sell":100,"armorType":"head","armorSet":"Chester's","iconId":1310,"defN":12,"defSl":12,"defSt":16.2,"defTh":12,"defM":13,"defF":9,"defL":12,"defP":0,"defT":14,"defB":19,"defC":0,"upgradeId":100},{"id":701000,"name":"Chester's Long Coat","itemType":"armor","dur":100,"weight":4.5,"sell":100,"armorType":"chest","armorSet":"Chester's","iconId":1311,"defN":27,"defSl":27,"defSt":36.5,"defTh":27,"defM":30,"defF":21,"defL":28,"defP":0,"defT":32,"defB":44,"defC":0,"upgradeId":100},{"id":702000,"name":"Chester's Gloves","itemType":"armor","dur":100,"weight":1.5,"sell":100,"armorType":"hands","armorSet":"Chester's","iconId":1312,"defN":10,"defSl":10,"defSt":13.5,"defTh":10,"defM":10,"defF":7,"defL":10,"defP":0,"defT":11,"defB":15,"defC":0,"upgradeId":100},{"id":703000,"name":"Chester's Trousers","itemType":"armor","dur":100,"weight":3.2,"sell":100,"armorType":"legs","armorSet":"Chester's","iconId":1313,"defN":19,"defSl":19,"defSt":25.6,"defTh":19,"defM":21,"defF":15,"defL":20,"defP":0,"defT":23,"defB":31,"defC":0,"upgradeId":100},{"id":710000,"name":"Bloated Head","itemType":"armor","dur":100,"weight":2.5,"sell":100,"armorType":"head","armorSet":"","iconId":1314,"defN":17,"defSl":17,"defSt":17,"defTh":17,"defM":17,"defF":9,"defL":11,"defP":0,"defT":32,"defB":16,"defC":10,"upgradeId":-1},{"id":720000,"name":"Bloated Sorcerer Head","itemType":"armor","dur":100,"weight":2.2,"sell":100,"armorType":"head","armorSet":"","iconId":1315,"defN":14,"defSl":14,"defSt":14,"defTh":14,"defM":22,"defF":9,"defL":13,"defP":0,"defT":38,"defB":8,"defC":15,"upgradeId":-1}]